ptlflow/__init__.py
ptlflow/data/AutoFlow_val.txt
ptlflow/data/FlyingChairs_val.txt
ptlflow/data/Hd1k_val.txt
ptlflow/data/Kitti2012_val.txt
ptlflow/data/Kitti2015_val.txt
ptlflow/data/Sintel_val.txt
ptlflow/data/__init__.py
ptlflow/data/datasets.py
ptlflow/data/flow_datamodule.py
ptlflow/data/flow_transforms.py
ptlflow/data/split_autoflow.py
ptlflow/models/README.md
ptlflow/models/__init__.py
ptlflow/models/base_model/__init__.py
ptlflow/models/base_model/base_model.py
ptlflow/models/ccmr/LICENSE
ptlflow/models/ccmr/README.md
ptlflow/models/ccmr/__init__.py
ptlflow/models/ccmr/ccmr.py
ptlflow/models/ccmr/corr.py
ptlflow/models/ccmr/extractor.py
ptlflow/models/ccmr/helpers.py
ptlflow/models/ccmr/update.py
ptlflow/models/ccmr/utils.py
ptlflow/models/ccmr/xcit.py
ptlflow/models/craft/LICENSE
ptlflow/models/craft/README.md
ptlflow/models/craft/__init__.py
ptlflow/models/craft/corr.py
ptlflow/models/craft/craft.py
ptlflow/models/craft/extractor.py
ptlflow/models/craft/gma.py
ptlflow/models/craft/setrans.py
ptlflow/models/craft/setrans_ablation.py
ptlflow/models/craft/update.py
ptlflow/models/craft/utils.py
ptlflow/models/csflow/LICENSE
ptlflow/models/csflow/README.md
ptlflow/models/csflow/__init__.py
ptlflow/models/csflow/csflow.py
ptlflow/models/dicl/README.md
ptlflow/models/dicl/__init__.py
ptlflow/models/dicl/dicl.py
ptlflow/models/dicl/loss_functions.py
ptlflow/models/dip/LICENSE
ptlflow/models/dip/README.md
ptlflow/models/dip/__init__.py
ptlflow/models/dip/corr.py
ptlflow/models/dip/dip.py
ptlflow/models/dip/extractor.py
ptlflow/models/dip/path_match.py
ptlflow/models/dip/update.py
ptlflow/models/dip/utils.py
ptlflow/models/dpflow/LICENSE
ptlflow/models/dpflow/README.md
ptlflow/models/dpflow/__init__.py
ptlflow/models/dpflow/cgu.py
ptlflow/models/dpflow/cgu_bidir_dual_encoder.py
ptlflow/models/dpflow/conv.py
ptlflow/models/dpflow/corr.py
ptlflow/models/dpflow/dpflow.py
ptlflow/models/dpflow/norm.py
ptlflow/models/dpflow/pwc_modules.py
ptlflow-0.4.1.dist-info/licenses/LICENSE
ptlflow-0.4.1.dist-info/METADATA
ptlflow-0.4.1.dist-info/WHEEL
ptlflow-0.4.1.dist-info/top_level.txt
ptlflow-0.4.1.dist-info/RECORD
