Metadata-Version: 2.4
Name: ptlflow
Version: 0.4.1
Summary: PyTorch Lightning Optical Flow
Author-email: Henrique Morimitsu <henriquem87@gmail.com>
License: Apache 2.0 License
Project-URL: Source Code, https://github.com/hmorimitsu/ptlflow
Project-URL: Documentation, https://ptlflow.readthedocs.io/
Keywords: torch,pytorch lightning,optical flow,models
Classifier: Development Status :: 3 - Alpha
Classifier: Intended Audience :: Education
Classifier: Intended Audience :: Science/Research
Classifier: License :: OSI Approved :: Apache Software License
Classifier: Programming Language :: Python :: 3
Classifier: Programming Language :: Python :: 3.10
Classifier: Programming Language :: Python :: 3.11
Classifier: Programming Language :: Python :: 3.12
Classifier: Topic :: Scientific/Engineering
Classifier: Topic :: Scientific/Engineering :: Artificial Intelligence
Classifier: Topic :: Software Development
Classifier: Topic :: Software Development :: Libraries
Classifier: Topic :: Software Development :: Libraries :: Python Modules
Requires-Python: <3.13,>=3.8
License-File: LICENSE
Requires-Dist: einops<0.9
Requires-Dist: h5py<3.13
Requires-Dist: kaleido<0.3
Requires-Dist: lightning[pytorch-extra]<2.6,>=2.1
Requires-Dist: loguru<0.8
Requires-Dist: opencv-python<4.11
Requires-Dist: pandas<2.3
Requires-Dist: plotly<5.25
Requires-Dist: pypng==0.20220715.0
Requires-Dist: scipy<1.15
Requires-Dist: tabulate<0.10
Requires-Dist: tensorboard<2.19
Requires-Dist: timm<1.1
Dynamic: license-file
